dynast/__init__.py
dynast/cli.py
dynast/dynast_manager.py
dynast/version.py
dynast/analytics/__init__.py
dynast/analytics/results.py
dynast/analytics/visualize.py
dynast/measure/__init__.py
dynast/measure/latency.py
dynast/predictors/__init__.py
dynast/predictors/dynamic_predictor.py
dynast/predictors/predictor_manager.py
dynast/search/__init__.py
dynast/search/encoding.py
dynast/search/evaluation_interface.py
dynast/search/evolutionary.py
dynast/search/search_tactic.py
dynast/supernetwork/__init__.py
dynast/supernetwork/supernetwork_registry.py
dynast/supernetwork/image_classification/__init__.py
dynast/supernetwork/image_classification/bootstrapnas/__init__.py
dynast/supernetwork/image_classification/bootstrapnas/bootstrapnas_encoding.py
dynast/supernetwork/image_classification/bootstrapnas/bootstrapnas_interface.py
dynast/supernetwork/image_classification/ofa/__init__.py
dynast/supernetwork/image_classification/ofa/ofa_encoding.py
dynast/supernetwork/image_classification/ofa/ofa_interface.py
dynast/supernetwork/image_classification/ofa/ofa/__init__.py
dynast/supernetwork/image_classification/ofa/ofa/model_zoo.py
dynast/supernetwork/image_classification/ofa/ofa/imagenet_classification/__init__.py
dynast/supernetwork/image_classification/ofa/ofa/imagenet_classification/data_providers/__init__.py
dynast/supernetwork/image_classification/ofa/ofa/imagenet_classification/data_providers/base_provider.py
dynast/supernetwork/image_classification/ofa/ofa/imagenet_classification/data_providers/imagenet.py
dynast/supernetwork/image_classification/ofa/ofa/imagenet_classification/elastic_nn/__init__.py
dynast/supernetwork/image_classification/ofa/ofa/imagenet_classification/elastic_nn/utils.py
dynast/supernetwork/image_classification/ofa/ofa/imagenet_classification/elastic_nn/modules/__init__.py
dynast/supernetwork/image_classification/ofa/ofa/imagenet_classification/elastic_nn/modules/dynamic_layers.py
dynast-1.6.0.dist-info/LICENSE.md
dynast-1.6.0.dist-info/METADATA
dynast-1.6.0.dist-info/WHEEL
dynast-1.6.0.dist-info/entry_points.txt
dynast-1.6.0.dist-info/top_level.txt
dynast-1.6.0.dist-info/RECORD
