Metadata-Version: 2.1
Name: dynast
Version: 1.6.0
Summary: DyNAS-T (Dynamic Neural Architecture Search Toolkit) - a SuperNet NAS optimization package
Author: Maciej Szankin, Sharath Nittur Sridhar, Anthony Sarah, Sairam Sundaresan
Author-email: maciej.szankin@intel.com, sharath.nittur.sridhar@intel.com, anthony.sarah@intel.com, sairam.sundaresan@intel.com
License: Apache 2.0
Classifier: Intended Audience :: Science/Research
Classifier: Programming Language :: Python
Classifier: Programming Language :: Python :: 3
Classifier: Programming Language :: Python :: 3.7
Classifier: Programming Language :: Python :: 3.8
Classifier: Programming Language :: Python :: 3.9
Classifier: Programming Language :: Python :: 3.10
Classifier: Topic :: Scientific/Engineering :: Artificial Intelligence
Classifier: License :: OSI Approved :: Apache Software License
Classifier: Operating System :: OS Independent
Requires-Python: >=3.7.0
License-File: LICENSE.md
Requires-Dist: autograd (>=1.5)
Requires-Dist: fairseq (>=0.12.2)
Requires-Dist: gdown
Requires-Dist: numba (>=0.56.4)
Requires-Dist: numpy (>=1.21.6)
Requires-Dist: pandas (>=1.3.5)
Requires-Dist: pymoo (>=0.6.0)
Requires-Dist: requests (>=2.28.1)
Requires-Dist: sacremoses (>=0.0.53)
Requires-Dist: scikit-learn (>=1.0.2)
Requires-Dist: scipy (>=1.7.3)
Requires-Dist: torch (>=1.12.0)
Requires-Dist: torchprofile (>=0.0.4)
Requires-Dist: torchvision (>=0.13.0)
Requires-Dist: transformers (>=4.10.0)
Provides-Extra: all
Requires-Dist: addict ; extra == 'all'
Requires-Dist: autograd (>=1.5) ; extra == 'all'
Requires-Dist: black ; extra == 'all'
Requires-Dist: fairseq (>=0.12.2) ; extra == 'all'
Requires-Dist: flake8 ; extra == 'all'
Requires-Dist: flake8-html ; extra == 'all'
Requires-Dist: gdown ; extra == 'all'
Requires-Dist: isort ; extra == 'all'
Requires-Dist: jstyleson ; extra == 'all'
Requires-Dist: mypy ; extra == 'all'
Requires-Dist: neural-compressor ; extra == 'all'
Requires-Dist: numba (>=0.56.4) ; extra == 'all'
Requires-Dist: numpy (>=1.21.6) ; extra == 'all'
Requires-Dist: pandas (>=1.3.5) ; extra == 'all'
Requires-Dist: pymoo (>=0.6.0) ; extra == 'all'
Requires-Dist: pytest ; extra == 'all'
Requires-Dist: pytest-cov ; extra == 'all'
Requires-Dist: requests (>=2.28.1) ; extra == 'all'
Requires-Dist: sacremoses (>=0.0.53) ; extra == 'all'
Requires-Dist: scikit-learn (>=1.0.2) ; extra == 'all'
Requires-Dist: scipy (>=1.7.3) ; extra == 'all'
Requires-Dist: tensorboard ; extra == 'all'
Requires-Dist: texttable ; extra == 'all'
Requires-Dist: torch (>=1.12.0) ; extra == 'all'
Requires-Dist: torchprofile (>=0.0.4) ; extra == 'all'
Requires-Dist: torchvision (>=0.13.0) ; extra == 'all'
Requires-Dist: tox ; extra == 'all'
Requires-Dist: transformers (>=4.10.0) ; extra == 'all'
Requires-Dist: pymarkdownlnt ; (python_version >= "3.8") and extra == 'all'
Provides-Extra: bootstrapnas
Requires-Dist: addict ; extra == 'bootstrapnas'
Requires-Dist: autograd (>=1.5) ; extra == 'bootstrapnas'
Requires-Dist: fairseq (>=0.12.2) ; extra == 'bootstrapnas'
Requires-Dist: gdown ; extra == 'bootstrapnas'
Requires-Dist: jstyleson ; extra == 'bootstrapnas'
Requires-Dist: numba (>=0.56.4) ; extra == 'bootstrapnas'
Requires-Dist: numpy (>=1.21.6) ; extra == 'bootstrapnas'
Requires-Dist: pandas (>=1.3.5) ; extra == 'bootstrapnas'
Requires-Dist: pymoo (>=0.6.0) ; extra == 'bootstrapnas'
Requires-Dist: requests (>=2.28.1) ; extra == 'bootstrapnas'
Requires-Dist: sacremoses (>=0.0.53) ; extra == 'bootstrapnas'
Requires-Dist: scikit-learn (>=1.0.2) ; extra == 'bootstrapnas'
Requires-Dist: scipy (>=1.7.3) ; extra == 'bootstrapnas'
Requires-Dist: tensorboard ; extra == 'bootstrapnas'
Requires-Dist: texttable ; extra == 'bootstrapnas'
Requires-Dist: torch (>=1.12.0) ; extra == 'bootstrapnas'
Requires-Dist: torchprofile (>=0.0.4) ; extra == 'bootstrapnas'
Requires-Dist: torchvision (>=0.13.0) ; extra == 'bootstrapnas'
Requires-Dist: transformers (>=4.10.0) ; extra == 'bootstrapnas'
Provides-Extra: neural_compressor
Requires-Dist: autograd (>=1.5) ; extra == 'neural_compressor'
Requires-Dist: fairseq (>=0.12.2) ; extra == 'neural_compressor'
Requires-Dist: gdown ; extra == 'neural_compressor'
Requires-Dist: neural-compressor ; extra == 'neural_compressor'
Requires-Dist: numba (>=0.56.4) ; extra == 'neural_compressor'
Requires-Dist: numpy (>=1.21.6) ; extra == 'neural_compressor'
Requires-Dist: pandas (>=1.3.5) ; extra == 'neural_compressor'
Requires-Dist: pymoo (>=0.6.0) ; extra == 'neural_compressor'
Requires-Dist: requests (>=2.28.1) ; extra == 'neural_compressor'
Requires-Dist: sacremoses (>=0.0.53) ; extra == 'neural_compressor'
Requires-Dist: scikit-learn (>=1.0.2) ; extra == 'neural_compressor'
Requires-Dist: scipy (>=1.7.3) ; extra == 'neural_compressor'
Requires-Dist: torch (>=1.12.0) ; extra == 'neural_compressor'
Requires-Dist: torchprofile (>=0.0.4) ; extra == 'neural_compressor'
Requires-Dist: torchvision (>=0.13.0) ; extra == 'neural_compressor'
Requires-Dist: transformers (>=4.10.0) ; extra == 'neural_compressor'
Provides-Extra: test
Requires-Dist: autograd (>=1.5) ; extra == 'test'
Requires-Dist: black ; extra == 'test'
Requires-Dist: fairseq (>=0.12.2) ; extra == 'test'
Requires-Dist: flake8 ; extra == 'test'
Requires-Dist: flake8-html ; extra == 'test'
Requires-Dist: gdown ; extra == 'test'
Requires-Dist: isort ; extra == 'test'
Requires-Dist: mypy ; extra == 'test'
Requires-Dist: numba (>=0.56.4) ; extra == 'test'
Requires-Dist: numpy (>=1.21.6) ; extra == 'test'
Requires-Dist: pandas (>=1.3.5) ; extra == 'test'
Requires-Dist: pymoo (>=0.6.0) ; extra == 'test'
Requires-Dist: pytest ; extra == 'test'
Requires-Dist: pytest-cov ; extra == 'test'
Requires-Dist: requests (>=2.28.1) ; extra == 'test'
Requires-Dist: sacremoses (>=0.0.53) ; extra == 'test'
Requires-Dist: scikit-learn (>=1.0.2) ; extra == 'test'
Requires-Dist: scipy (>=1.7.3) ; extra == 'test'
Requires-Dist: torch (>=1.12.0) ; extra == 'test'
Requires-Dist: torchprofile (>=0.0.4) ; extra == 'test'
Requires-Dist: torchvision (>=0.13.0) ; extra == 'test'
Requires-Dist: tox ; extra == 'test'
Requires-Dist: transformers (>=4.10.0) ; extra == 'test'
Requires-Dist: pymarkdownlnt ; (python_version >= "3.8") and extra == 'test'
